pandoc_eqnos.py
pandoc_eqnos-2.5.0.dist-info/AUTHORS
pandoc_eqnos-2.5.0.dist-info/LICENSE
pandoc_eqnos-2.5.0.dist-info/METADATA
pandoc_eqnos-2.5.0.dist-info/WHEEL
pandoc_eqnos-2.5.0.dist-info/entry_points.txt
pandoc_eqnos-2.5.0.dist-info/top_level.txt
pandoc_eqnos-2.5.0.dist-info/RECORD
